fastapi_praisonai/__init__.py
fastapi_praisonai/client.py
fastapi_praisonai/router.py
fastapi_praisonai-0.1.0.dist-info/licenses/LICENSE
fastapi_praisonai-0.1.0.dist-info/METADATA
fastapi_praisonai-0.1.0.dist-info/WHEEL
fastapi_praisonai-0.1.0.dist-info/top_level.txt
fastapi_praisonai-0.1.0.dist-info/RECORD
